concrete_hnp-0.0.10-py3.9-nspkg.pth
concrete/hnp/__init__.py
concrete/hnp/file.py
concrete_hnp-0.0.10.dist-info/LICENSE
concrete_hnp-0.0.10.dist-info/METADATA
concrete_hnp-0.0.10.dist-info/WHEEL
concrete_hnp-0.0.10.dist-info/namespace_packages.txt
concrete_hnp-0.0.10.dist-info/top_level.txt
concrete_hnp-0.0.10.dist-info/RECORD
